{
    "photographies": [
        {
            "chemin":"hivernies.png",
            "nom":"Hivernies",
            "photographe":"Patrick BOGNER",
            "description":"",
            "theme":"paysage",
            "couleur":"gris"
        },
        {
            "chemin":"bayle.png",
            "nom":"Bayle",
            "photographe":"François BOUTAUD",
            "description":"",
            "theme":"abstrait",
            "couleur":"noir"
        },
        {
            "chemin":"IAmFoldingTheLand.png",
            "nom":"I Am Folding the Land",
            "photographe":"Catherine CATTARUZZA",
            "description":"",
            "theme":"paysage",
            "couleur":"jaune"
        },
        {
            "chemin":"khamseen.png",
            "nom":"Khamseen",
            "photographe":"Leah DESMOUSSEAUX",
            "description":"",
            "theme":"paysage",
            "couleur":"gris"
        },
        {
            "chemin":"laMainInvisible.png",
            "nom":"La Main invisible",
            "photographe":"Thierry FOURNIER",
            "description":"",
            "theme":"abstrait",
            "couleur":"bleu"
        },
        {
            "chemin":"nonLieu.png",
            "nom":"Non-Lieu",
            "photographe":"Thierry FOURNIER",
            "description":"",
            "theme":"paysage",
            "couleur":"gris"
        },
        {
            "chemin":"portraitOfALandscape.png",
            "nom":"Portrait of a landscape",
            "photographe":"Pierre-Philippe HOFMANN",
            "description":"",
            "theme":"paysage",
            "couleur":"gris"
        },
        {
            "chemin":"intersection.png",
            "nom":"Intersection",
            "photographe":"Mélanie-Jane FREY",
            "description":"",
            "theme":"abstrait",
            "couleur":"bleu"
        },
        {
            "chemin":"eresUnaMaravilla.png",
            "nom":"Eres una maravilla",
            "photographe":"Magali LAMBERT",
            "description":"",
            "theme":"abstrait",
            "couleur":"noir"
        },
        {
            "chemin":"ostende.png",
            "nom":"Ostende",
            "photographe":"Yvon LAMBERT",
            "description":"",
            "theme":"abstrait",
            "couleur":"gris"
        },
        {
            "chemin":"pleasuresAndTerrorsOfLevitationII.png",
            "nom":"Pleasures and Terrors of Levitation II",
            "photographe":"François LAXALT",
            "description":"",
            "theme":"abstrait",
            "couleur":"gris"
        },
        {
            "chemin":"uneRespirationDeCombat.png",
            "nom":"Une Respiration de combat",
            "photographe":"Elli LORZ",
            "description":"",
            "theme":"portrait",
            "couleur":"noir"
        },
        {
            "chemin":"identitesDeChantier.png",
            "nom":"Identités en chantier",
            "photographe":"Elli LORZ",
            "description":"",
            "theme":"paysage",
            "couleur":"bleu"
        },
        {
            "chemin":"prisesDeVie.png",
            "nom":"Prises de vie",
            "photographe":"Françoise SAUR",
            "description":"",
            "theme":"portrait",
            "couleur":"gris"
        },
        {
            "chemin":"lesMauvaisesHerbes.png",
            "nom":"Les mauvaises herbes",
            "photographe":"Anaïs ONDET",
            "description":"",
            "theme":"portrait",
            "couleur":"noir"
        },
        {
            "chemin":"jeFixeraiDesVertiges.png",
            "nom":"Je fixerai des vertiges",
            "photographe":"Georges PACHECO",
            "description":"",
            "theme":"portrait",
            "couleur":"noir"
        },
        {
            "chemin":"danseAvecLaTerre.png",
            "nom":"Danse avec la Terre . RONDO",
            "photographe":"Jakub PAJEWSKI",
            "description":"",
            "theme":"abstrait",
            "couleur":"noir"
        },
        {
            "chemin":"faillesEntreLieuxEtNonLieux.png",
            "nom":"Failles, entre lieux et non-lieux",
            "photographe":"Franck POURCEL",
            "description":"",
            "theme":"paysage",
            "couleur":"bleu"
        },
        {
            "chemin":"travauxDesChamps.png",
            "nom":"Travaux des champs",
            "photographe":"Myriam RICHARD",
            "description":"",
            "theme":"portrait",
            "couleur":"bleu"
        },
        {
            "chemin":"sleeplessCountry.png",
            "nom":"Sleepless country",
            "photographe":"Adrienne SURPRENANT",
            "description":"",
            "theme":"portrait",
            "couleur":"noir"
        },
        {
            "chemin":"kar.png",
            "nom":"քար [k’ar]",
            "photographe":"Sarkis TOROSSIAN",
            "description":"",
            "theme":"paysage",
            "couleur":"gris"
        },
        {
            "chemin":"oneiros.png",
            "nom":"Óneiros",
            "photographe":"Armelle TULUNDA",
            "description":"",
            "theme":"abstrait",
            "couleur":"noir"
        },
        {
            "chemin":"surLaTerreCommeAuCiel.png",
            "nom":"Sur la terre comme au ciel",
            "photographe":"Armelle TULUNDA",
            "description":"",
            "theme":"abstrait",
            "couleur":"noir"
        },
        {
            "chemin":"samedi25avril.png",
            "nom":"Samedi 25 avril 2015, 13 heures",
            "photographe":"Joël VAN AUDENHAEGE",
            "description":"",
            "theme":"paysage",
            "couleur":"noir"
        },
        {
            "chemin":"MasaoYAMAMOTO.png",
            "nom":"",
            "photographe":"Masao YAMAMOTO",
            "description":"",
            "theme":"abstrait",
            "couleur":"noir"
        },
        {
            "chemin":"FrançoisTUEFFERD.png",
            "nom":"",
            "photographe":"François TUEFFERD",
            "description":"",
            "theme":"abstrait",
            "couleur":"noir"
        },
        {
            "chemin":"onStreet.png",
            "nom":"On street",
            "photographe":"Igor EFIMOV",
            "description":"",
            "theme":"portrait",
            "couleur":"jaune"
        },
        {
            "chemin":"calmWaters.png",
            "nom":"Calm Waters",
            "photographe":"Andriy LOMAKIN",
            "description":"",
            "theme":"portrait",
            "couleur":"gris"
        },
        {
            "chemin":"space.png",
            "nom":"Space",
            "photographe":"Yulia CHERVISNKA",
            "description":"",
            "theme":"abstrait",
            "couleur":"bleu"
        },
        {
            "chemin":"grandmothersOnTheEdgeOfHeaven.png",
            "nom":"Grandmothers on the Edge of Heaven",
            "photographe":"Elena SUBACH",
            "description":"",
            "theme":"portrait",
            "couleur":"bleu"
        },
        {
            "chemin":"LVIV.png",
            "nom":"LVIV——GOD’S WILL",
            "photographe":"Viacheslav POLIAKOV",
            "description":"",
            "theme":"portrait",
            "couleur":"jaune"
        },
        {
            "chemin":"inspiration4.png",
            "nom":"Inspiration 4",
            "photographe":"Émilie SALQUÈBRE",
            "description":"",
            "theme":"abstrait",
            "couleur":"gris"
        },
        {
            "chemin":"nosPaysagesInterieurs.png",
            "nom":"Nos paysages intérieurs",
            "photographe":"Valentine ZELER",
            "description":"",
            "theme":"paysage",
            "couleur":"noir"
        },
        {
            "chemin":"ThiloSEIDEL.png",
            "nom":"",
            "photographe":"Thilo SEIDEL",
            "description":"",
            "theme":"paysage",
            "couleur":"noir"
        },
        {
            "chemin":"Anne-sophieCOSTENOBLE.png",
            "nom":"",
            "photographe":"Anne-sophie COSTENOBLE",
            "description":"",
            "theme":"paysage",
            "couleur":"noir"
        },
        {
            "chemin":"teCassePasLaTete.png",
            "nom":"Te casse pas la tête",
            "photographe":"Baptiste COZZUPOLI",
            "description":"",
            "theme":"portrait",
            "couleur":"noir"
        }
    ]
}